<?xml version="1.0" encoding="UTF-8"?>
<!--
  @package   AkeebaReleaseSystem
  @copyright Copyright (c)2010-2017 Nicholas K. Dionysopoulos
  @license   GNU General Public License version 3, or later
-->
<form type="browse" show_header="1" show_filters="1" show_pagination="1"
      norows_placeholder="COM_ARS_COMMON_NOITEMS_LABEL"
      cssfiles="media://com_ars/css/backend.css">

    <headerset>
        <header name="ordering" type="Ordering" label="JFIELD_ORDERING_LABEL" sortable="true" tdwidth="1%"/>
        <header name="id" type="RowSelect" label="JGLOBAL_FIELD_ID_LABEL" sortable="true" tdwidth="20"/>
        <header name="title" type="Searchable" label="LBL_VGROUPS_TITLE"/>
        <header name="published" type="Published" label="JPUBLISHED" sortable="true" tdwidth="10%"/>
    </headerset>
    <fieldset name="items">
        <field name="ordering" type="Ordering" class="input-mini input-sm"/>
        <field name="id" type="SelectRow"/>
        <field name="title" type="Text"
               url="index.php?option=com_ars&amp;view=VisualGroup&amp;id=[ITEM:ID]"/>
        <field name="published" type="Actions" label="COM_ARS_VISUALGROUPS_PUBLISHED_LBL"/>
    </fieldset>
</form>
