{
	"$schema": "https://developer.joomla.org/schemas/json-schema/web_assets.json",
	"name": "com_ars",
	"version": "7.0.8",
	"description": "Akeeba Release System",
	"license": "GPL-3.0-or-later",
	"assets": [
		{
			"name": "com_ars.backend_light",
			"description": "Common backend user interface CSS, light mode",
			"type": "style",
			"uri": "com_ars/backend.css"
		},

		{
			"name": "com_ars.frontend_light",
			"description": "Common frontend user interface CSS, light mode",
			"type": "style",
			"uri": "com_ars/frontend.css"
		},

		{
			"name": "com_ars.chart",
			"description": "Charts.js — renders charts and graphs",
			"type": "script",
			"uri": "https://cdn.jsdelivr.net/npm/chart.js@3.2.1/dist/chart.min.js",
			"attributes": {
				"defer": true
			}
		},
		{
			"name": "com_ars.chart_moment_adapter",
			"description": "Moment adapter for Charts.js",
			"type": "script",
			"dependencies": [
				"com_ars.chart",
				"com_ars.moment"
			],
			"uri": "https://cdn.jsdelivr.net/npm/chartjs-adapter-moment@0.1.1",
			"attributes": {
				"defer": true
			}
		},
		{
			"name": "com_ars.moment",
			"description": "Moment — handles date conversions in JavaScript",
			"type": "script",
			"uri": "https://cdn.jsdelivr.net/npm/moment@2.27.0",
			"attributes": {
				"defer": true
			}
		},

		{
			"name": "com_ars.gui-helpers",
			"description": "Common JavaScript",
			"type": "script",
			"uri": "com_ars/gui-helpers.min.js",
			"dependencies": [
				"core"
			],
			"attributes": {
				"defer": true
			}
		},

		{
			"name": "com_ars.controlpanel",
			"description": "JavaScript for the Control Panel page",
			"type": "script",
			"uri": "com_ars/ControlPanel.min.js",
			"dependencies": [
				"core",
				"com_ars.chart_moment_adapter"
			],
			"attributes": {
				"defer": true
			}
		},
		{
			"name": "com_ars.items",
			"description": "JavaScript for managing items in the backend",
			"type": "script",
			"uri": "com_ars/Items.min.js",
			"dependencies": [
				"core",
				"com_ars.gui-helpers"
			],
			"attributes": {
				"defer": true
			}
		},
		{
			"name": "com_ars.item_select",
			"description": "JavaScript for managing item selection in the front- or backend",
			"type": "script",
			"uri": "com_ars/ItemSelect.min.js",
			"dependencies": [
				"core"
			],
			"attributes": {
				"defer": true
			}
		},
		{
			"name": "com_ars.copy_button",
			"description": "JavaScript to implement the copy to clipboard button",
			"type": "script",
			"uri": "com_ars/CopyButton.min.js",
			"dependencies": [
				"core"
			],
			"attributes": {
				"defer": true
			}
		},

		{
			"name": "com_ars.backend",
			"type": "preset",
			"dependencies": [
				"com_ars.backend_light#style",

				"com_ars.gui-helpers#script"
			]
		},
		{
			"name": "com_ars.frontend",
			"type": "preset",
			"dependencies": [
				"com_ars.frontend_light#style"
			]
		}
	]
}